{
  "batchName": "",
  "batchTime": 1710153837,
  "boardConf": "nIR-C00M00-00",
  "boardCustom": "",
  "boardName": "NG9093",
  "boardOptions": 0,
  "boardRev": "R3M0E4",
  "cameraData": [
    [
      0,
      {
        "cameraType": 0,
        "distortionCoeff": [
          0.0,
          0.0,
          0.0,
          0.0,
          0.0
        ],
        "extrinsics": {
          "rotationMatrix": [
            [
              0.0,
              0.0,
              0.0
            ],
            [
              0.0,
              0.0,
              0.0
            ],
            [
              0.0,
              0.0,
              0.0
            ]
          ],
          "specTranslation": {
            "x": -0.0,
            "y": -0.0,
            "z": -0.0
          },
          "toCameraSocket": -1,
          "translation": {
            "x": 0.0,
            "y": 0.0,
            "z": 0.0
          }
        },
        "height": 2160,
        "intrinsicMatrix": [
          [
            586.4889526367188,
            0.0,
            640.0
          ],
          [
            0.0,
            586.4889478683472,
            360.0
          ],
          [
            0.0,
            0.0,
            1.0
          ]
        ],
        "lensPosition": 0,
        "specHfovDeg": 108.0,
        "width": 3840
      }
    ]
  ],
  "deviceName": "",
  "hardwareConf": "F1-FV01-BC000",
  "housingExtrinsics": {
    "rotationMatrix": [],
    "specTranslation": {
      "x": 0.0,
      "y": 0.0,
      "z": 0.0
    },
    "toCameraSocket": -1,
    "translation": {
      "x": 0.0,
      "y": 0.0,
      "z": 0.0
    }
  },
  "imuExtrinsics": {
    "rotationMatrix": [
      [
        0.0,
        0.0,
        0.0
      ],
      [
        0.0,
        0.0,
        0.0
      ],
      [
        0.0,
        0.0,
        0.0
      ]
    ],
    "specTranslation": {
      "x": 0.0,
      "y": 0.0,
      "z": 0.0
    },
    "toCameraSocket": -1,
    "translation": {
      "x": 0.0,
      "y": 0.0,
      "z": 0.0
    }
  },
  "miscellaneousData": [],
  "productName": "OAK-1-W",
  "stereoEnableDistortionCorrection": true,
  "stereoRectificationData": {
    "leftCameraSocket": 255,
    "rectifiedRotationLeft": [
      [
        0.0,
        0.0,
        0.0
      ],
      [
        0.0,
        0.0,
        0.0
      ],
      [
        0.0,
        0.0,
        0.0
      ]
    ],
    "rectifiedRotationRight": [
      [
        0.0,
        0.0,
        0.0
      ],
      [
        0.0,
        0.0,
        0.0
      ],
      [
        0.0,
        0.0,
        0.0
      ]
    ],
    "rightCameraSocket": 255
  },
  "stereoUseSpecTranslation": false,
  "version": 7,
  "verticalCameraSocket": -1
}